Workbook

Sheet Sheet2
A1: RG | H1: terraform{
A2: Vnet | I2: required_providers{
A3: Subnet | J3: azurerm = {
A4: NIC | K4: source = "hashicorp\azurerm"
A5: NSG | K5: version = "4.38.0"
A6: NIC-NSG association | K6: }
A7: Public Ip | J7: }
A8: VM _ Linux VM | I8: }
A10: ACR
A11: AKS | H11: provider "azurerm" {
A12: MySQL Server | I12: features{}
A13: MySQL Database | I13: subscription_id= ""
A14: firewalls Rulles | I14: }
A16: k8s
A17: Deployment.yml | H17: resource "azurerm_resource_group" "rgs" {
A18: PV.yml | H18: name = ""
A19: PVC.yml | H19: location = ""
A20: Service.yml | H20: }
A21: Ingress.Yml
H23: resource "azurerm_virtual_network" "vnet" {
H24: name = ""
H25: resource_group_name =""
H26: location = ""
H27: address_space = ["10.0.0.0/16"]
H28: }
H31: resource "azurerm_subnet" "subnet" {
H32: name = ""
H33: resource_group_name =""
H34: virtual_network_name =""
H35: address_prefixes = ["10.0.0.0/24"]
H36: }
... H51: ip_confiuration{
I52: name = "internal1"
I53: subnet_id = azurerm_subnet.subnet.id
I54: private_ip_address_allocation = "Dynamic"
I55: public_ip_address_id = azurerm_public_ip.pip.id
I56: }
H57: }
H60: resource "azurerm_network_security_group" "nsg" {
H61: name = ""
H62: resource_group_name =""
H63: location = ""
H64: security_rule{
I65: name= "SSH"
I66: priority=100
I67: direction="Inbound"
I68: access = "Allow"
I69: source_port_range =""
I70: destination_port_range =""
I71: source_address_prefixes =""
I72: destination_address_prefixes = ""
I73: protocol = ""
I74: }
H75: }
H78: resource "azurerm_network_interface_security_group_association" "nic_nsg" {
H79: network_interface_id = azurerm_network_interface.nic.id
H80: network_security_group_id = azurerm_network_security_group.nsg.id
H81: }
H84: resource "azurerm_linux_virtual_machine" "vm" {
H85: name = ""
H86: resource_group_name =""
H87: location = ""
H88: size = ""
H89: admin_unsername = ""
H90: admin_password = ""
... H94: os_disk{
I95: caching = "ReadWrite"
I96: storage_account_type="Standard_LRS"
I97: }
H99: source_image_reference{
I100: publisher= "Canonical"
I101: offer="0001-com-ubuntu-server-jammy"
I102: sku = "22_04-lts"
I103: version = latest"
I104: }
H105: }
H111: resource "azurerm_container_registry" "acr" {
I112: name = ""
I113: resource_group_name = ""
I114: location = ""
I115: sku = "Premium"
I116: admin_enabled = ""
I117: }
H120: resource "azurerm_kubernetes_cluster" "aks" {
I121: name = ""
I122: resource_group_name = ""
I123: location = ""
I124: dns_prefix = ""
I126: default_node_pool{
J127: name = ""
J128: node_count = 2
J129: vm_size = ""
J130: }
I132: identity{
J133: type = "SystemAssigned"
J134: }
H137: resource "azurerm_mysql_server" "server" {
I138: name = ""
I139: resource_group_name = ""
I140: location = ""
...

Sheet Nichod.tf
A1: Terraform | B1: 1 | C1: 6. What is a state file in Terraform?
A2: Terraform | C2: State file is the mind of terraform.
A3: Terraform | C3: A state file in Terraform is a file that keeps track of the current state of the infrastructure that Terraform manages.
A4: Terraform | C4: It maps the resources defined in the configuration to the real-world resources.
A5: Terraform | C5: The default file is named terraform.tfstate
A6: Terraform | C6: By default, Terraform stores the state file locally in the same directory where Terraform is run, as terraform.tfstate.
A7: Terraform | C7: It stores resource IDs, metadata, input variables, output values, dependencies, and the current state of all managed resources.
A8: Terraform | C8: .terraform directory --> holds provider plugins, modules, and workspace metadata used during operations like init, plan, and apply.
A9: Terraform | C9: Risk of saviing state file locally --> Local state is not shareable or lockable, overwrites, or inconsistent infrastructure changes.
A10: Terraform | C10: use of terraform.tfstate.backup --> It's a backup of the previous state file. Terraform creates or updates it automatically before writing a new terraform.tfstate.
A11: Terraform | C11: Benefit of storing remote backend --> remote access, team collaboration, state locking, versioning, and secure, centralized state management.
A12: Terraform
A13: Terraform | B13: 2 | C13: When a statefile will be created ?
A14: Terraform | C14: A state file is created when you run terraform init for the first time.
A15: Terraform
A16: Terraform | B16: 3 | C16: 7. Why is it important to manage the state file in Terraform?
A17: Terraform | C17: Managing the state file is crucial because it ensures consistency between the infrastructure's real state and the configuration.
A18: Terraform | C18: Terraform uses it to determine what resources exist, track metadata, and decide what changes to apply.
A19: Terraform
A20: Terraform | B20: 4 | C20: 8. How can you secure the state file in Terraform? /manage Terraform state files / Handle state file
A21: Terraform | C21: State files can be secured by storing them in remote backends with proper access controls and encryption, such as Azure blob storage with server-side encryption and access control policies.
A22: Terraform
A23: Terraform | B23: 5 | C23: 17. What is remote state(backend) and how do you configure it in Terraform?
A24: Terraform | C24: Remote state(Backend) allows Terraform to store the state file in a remote storage backend, enabling team collaboration and secure storage
A25: Terraform | C25: terraform { backend "azurerm" { resource_group_name = "Lavjeet-rg" storage_account_name = "mytfstatestorage" container_name = "tfstatestore" key = "terraform.tfstate" } }
A26: Terraform | C26: Run the terraform init command to initialize the backend and configure the state storage.
A27: Terraform
A28: Terraform | B28: 6 | C28: 22. What is a backend in Terraform?
A29: Terraform | C29: A backend in Terraform defines where and how the Terraform state file is stored.
A30: Terraform | C30: Benefits of keeping the Terraform state file in remote storage: It enables features like remote state storage,secure, state locking, and Collaboration (Enables multiple team members to work safely by locking state during changes)
A31: Terraform | C31: State Locking in Terraform prevents multiple people or processes from making changes to the infrastructure simultaneously.
A32: Terraform | C32: When you run Terraform plan or terraform apply commands, it locks the state file to ensure that only one operation is applied at a time. This avoids conflicts and ensures consistency in managing your resources.
A33: Terraform
A34: Terraform | B34: 7 | C34: 33. What is the terraform state command used for?
A35: Terraform | C35: The terraform state command is used to inspect and manage Terraform's state file. It helps you view or modify the state, including listing resources or moving resources within the stat
A36: Terraform | C36: terraform state list terraform state show azurerm_resource_group.rg1
A37: Terraform | C37: we can do --> terraform state
A38: Terraform | C38: list List resources in the state mv Move an item in the state pull Pull current state and output to stdout push Update remote state from a local state file replace-provider Replace provider in the state rm Remove resource from the state show Show a resource in the state
A39: Terraform
A40: Terraform | B40: 8 | C40: 55. What is the purpose of the terraform state mv command? /How do you rename a resource in the state file?
A41: Terraform | C41: A resource can be renamed in the state file using the terraform state mv command, which moves the state of a resource to a new address.
A42: Terraform | C42: terraform state mv azurerm_resource_group.old_name azurerm_resource_group.new_name
A43: Terraform
A44: Terraform | B44: 9 | C44: How do you handle state file conflicts in a team environment?
A45: Terraform | C45: Use remote state with locking enabled, run Terraform in CI/CD pipelines, and avoid local apply to reduce conflicts.
A46: Terraform
A47: Terraform | B47: 10 | C47: How would you manage sensitive data in Terraform state files?
A48: Terraform | C48: Avoid hardcoding secrets, use environment variables or secret managers, and secure the state file using encryption and limited access controls.
A49: Terraform
A50: Terraform | B50: 11 | C50: Have you ever had to manually edit a state file? If so, why and how did you do it safely?
A51: Terraform | C51: Yes, in rare cases to fix corruption or sync issues. Always back up the state first, use terraform state commands if possible, and manually edit JSON only as a last resort.
A52: Terraform
A53: Terraform | B53: 12 | C53: 65. How to Recover from Deleting the State File:
A54: Terraform | C54: Restore from Backup: If you have a backup of your terraform.tfstate file, restore it, and Terraform will resume managing your resources correctly. ( terraform will auto restore it once you hit terraform apply or refresh or init command)
A55: Terraform | C55: Re-import Resources:
A56: Terraform | C56: If no backup is available, you can use the terraform import command to re-import the existing resources into the state. This will allow Terraform to track the resources again without recreating them.
A57: Terraform | C57: terraform import <resource_type>.<resource_name> <resource_id>
A58: Terraform | C58: terraform import azurerm_resource_group.example /subscriptions/{subscription-id}/resourceGroups/example-resources
A59: Terraform | B59: 13 | C59: 64. If I delete the state file then what will happen
A60: Terraform | C60: 1. Loss of State Information:
A61: Terraform | C61: 2. Terraform Will Not Recognize Existing Resources: When you run terraform plan or terraform apply after deleting the state file, Terraform will assume that no resources exist and attempt to create them again, even if they already exist.
A62: Terraform | C62: 3. Potential for Infrastructure Drift: Without the state file, Terraform cannot track changes made outside Terraform
A63: Terraform | C63: 4. Unable to Destroy or Modify Resources Properly:
A64: Terraform
A65: Terraform | B65: 14 | C65: How to unlock state file
A66: Terraform | C66: terraform force -unlock < lock ID> # you can get lock id by running terraform plan command it will show
A67: Terraform | C67: 2nd way -> you can break lease from azure portal
A68: Terraform | C68: 3rd way-> using azure cli command --> azure storage account-break-lease
A69: Terraform
A70: Terraform | B70: 15 | C70: 18. How do you import existing resources into Terraform?
A71: Terraform | C71: Existing resources can be imported using the terraform import command, which maps the existing resource to a Terraform resource in the state file.
A72: Terraform | C72: Example:
A73: Terraform | C73: terraform import azurerm_resource_group.example /subscriptions/{subscription-id}/resourceGroups/example-resources
A74: Terraform | C74: terraform import <resource_type.resource_name> <resource_id>
A75: Terraform
A76: Terraform | B76: 16 | C76: How do you split or migrate Terraform state between modules or workspaces?
A77: Terraform | C77: Use terraform state mv to move resources between modules. For workspaces, Terraform maintains separate state files for each workspace.
A78: Terraform
A79: Terraform | B79: 17 | C79: What are the best practices for securing Terraform state files?
A80: Terraform | C80: Use encrypted backends, restrict access with IAM policies, avoid storing secrets in outputs, and use secret managers for sensitive values.
A81: Terraform
A82: Terraform | B82: 18 | C82: 11. What challenges have you faced managing state in a multi-cloud or hybrid environment?
A83: Terraform | C83: Challenges include state fragmentation, inconsistent backends, and increased risk of drift. Standardization and using Terraform Cloud or centralized remote backends help.
A84: Terraform
A85: Terraform | B85: 19 | C85: 9. What are modules in Terraform?
A86: Terraform | C86: In Terraform, modules is a way to organize and reuse infrastructure code / a set of resources, like virtual machines or networks, in multiple places.
A87: Terraform | C87: Modules is reusable packages of Terraform configurations that can be shared and composed to manage resources efficiently
A88: Terraform | C88: help avoid code duplicacy, simplify complex deployments, and allow teams to follow standard practices across environments.
A89: Terraform | C89: Example: module "vnet" { source = "./modules/vnet" }
A90: Terraform
A91: Terraform | B91: 20 | C91: what are the Types of modules
A92: Terraform | C92: Root Module: is the main working directory where Terraform is executed. and call child module Child Modules: Reusable modules that are called by the root module or other modules to organize and manage related resources. These modules help organize and reuse your Terraform code efficiently.
A93: Terraform
A94: Terraform | B94: 21 | C94: 44. How do you use output values across different modules in Terraform?
A95: Terraform | C95: Output values from one module can be referenced in another module by using the module's output attributes.
A96: Terraform | C96: module "network" { source = "./modules/network" } module "vm" { source = "./modules/vm" network_id = module.network.network_id }
A97: Terraform
A98: Terraform | B98: 22 | C98: 30. How do you manage module versioning in Terraform?
A99: Terraform | C99: Module versioning in Terraform is managed using the version argument in the module block.
A100: Terraform | C100: module "my_module" { source = "Azure/azurerm" version = "2.0.0" # we can use >=, ~>, etc., for flexibility. }
...

Sheet Nichod 2
A2: How you setup your Infra Pipeline
A3: Let me tell you how we setup our infra pipeline …
A4: I am assuming that my agent is online, azure repo /git repo and service conection is properly setup between azure portal and ado.
A5: what we do here is that, we are following trunk based branching strategy for our infra deployment
A6: So first we clone the code from repo to our local machine and then we make a feature branch and add whatever is beeing asked like VMs, subnet., in the tfvars file and then we do git add, git commit and git push by git push we push the code to repo
A7: and we rise PR to merge into the main branch. and as soon as we raise PR my pipeline will auto trigger, in this pipeline first satge is for scaning where we are using tfsec for security and vulnerabilities scanning, tflint for linting, code quality, to check unused varialble and best practivce check
A8: once it is passed then it goes for plan stage which includes terraform init, fmt, validate, and plan. By this stage we will get to know what are the resource is beging modiyfy or created or deleted and we redirect this output for future reference .
A9: then it goes for manual validation and apply stage, where approver can validated and verify scanning results and terraform plan. Once he is satisfied with plan then approve the manual validation and approve PR and then code is merged into main and then it goes for Terraform apply. and my resource will be created. and this is how we are doing it.
A12: How you setup your Application Pipeline
A13: In Application pipeline we follow git flow branching strategy , what it means is that branches are longer lived, like hot fixed , relased,
A14: I am assuming that devploer pushed the code by feature branch, as soon as he pushed the code it will trigger my pipeline and first it will for scanning stage where we are using sonarqube tool to check code quality ,Detect bugs, , code smells, vulnerabilities check. Detect bugs,
A15: once code is passed from scanning stage then it goes for next stage which is build stage. I am assuming that our code in reactjs so to build the artifact we require Node.js npm tool.
... A327: Azure Load Balancer – distribute traffic across VMs. --> RG --> Vnet --> Subnet --> Public IP -->"azurerm_lb" for frontend_ip_configuration -->azurerm_lb_backend_address_pool---> azurerm_lb_probe #(Health probe) --> azurerm_lb_rule --> azurerm_network_interface # NIC1 NIC2 NIC3 create muptile for muplitple vms --> azurerm_linux_virtual_machine #Vm1 Vm2 Vm3
A328: Azure Application Gateway – layer 7 load balancer with WAF. RG --> Vnet --> Subnet --> Public IP -->azurerm_application_gateway ## inside we many sub block like --> 1.sku 2. gateway_ip_configuration 3. frontend_port 4. frontend_ip_configuration 5. backend_address_pool 6. backend_addresses 7. backend_http_settings 8. http_listener 9. request_routing_rule | B328: sgff bbbhr
A329: Azure Kubernetes Service (AKS) – managed Kubernetes cluster. RG--> vnet --> subnet -> azurerm_kubernetes_cluster # sub block 1. default_node_pool 2. identity 3. network_profile 4. kube_config
A330: Azure Container Registry (ACR) – private container image repository. --> RG --> azurerm_container_registry
A331: Azure Monitor Log Analytics Workspace – centralized logging and monitoring.
A332: Azure Virtual Network Gateway – VPN gateway for site-to-site or point-to-site connectivity.
A335: Cluster Info --> kubectl version --->Show kubectl & server versions
A336: Cluster Info --> kubectl cluster-info --->Show cluster master & services
A337: Cluster Info --> kubectl get nodes --->List all worker nodes
A338: Cluster Info --> kubectl describe node <node> --->Detailed info about a node
A339: Namespaces --> kubectl get namespaces --->List all namespaces
A340: Namespaces --> kubectl create namespace dev --->Create namespace dev
A341: Namespaces --> kubectl delete namespace dev --->Delete namespace dev
A342: Namespaces --> kubectl config set-context --current --namespace=dev --->Set default namespace
... A382: Shortcuts --> alias kgn="kubectl get nodes" --->Shortcut for nodes

Sheet Tools
A2: Tool | B2: Primary Purpose | C2: What It Checks | D2: How to Run it
A3: tfsec | B3: Terraform security scanner | C3: Terraform IaC me security check, Infra vulnerabilities check (e.g., open security groups, hardcoded username password , unencrypted storage)
A4: tflint | B4: Terraform linter + code qulaity | C4: Detects Syntax issue+ check liniting ( grammar check )+ enforces best practices + provider-specific rules + Warn if an unused variable is declared + deprecated features + wrong instance type name problem --> Security nahi check karta, sirf linting | D4: tflint --init, tflint # if no output means all ok
A5: checkov | B5: IaC security + compliance scanner | C5: Multi-IaC security & compliance scanner — Terraform, Kubernetes, Helm, CloudFormation, ARM sab scan karta hai. Security misconfigs + Pre-built compliance policies + Policy Checks Check if all Kubernetes pods have resource limits set problem --> Thoda slow large repos me | D5: checkov -d . checkov -d . --framework terraform,kubernetes
A6: Trivy | B6: Vulnerability Scanning + container image scanning +Secret Scanning + Misconfiguration Scanning + Compliance Checks
A7: SonarQube | B7: Code quality + bug detection+ Detect Bugs + Continuous code quality tracking + security analysis + code smells | C7: Maintainability, code smells, security issues in application code (Java, Python, JS, etc.) | D7: Flag unused variables, SQL injection risk in code
A8: CodeQL | B8: Code security analyzer | C8: Deep semantic security analysis (application code, GitHub native) | D8: Find hardcoded credentials or unsafe input handling in code
B19: Ansible
B20: Ansible is an open-source automation tool used for:
B21: With the help of anible we can automate repetitive tasks, like installing software, starting services, Configuration management, Application deployment, Infrastructure provisioning, Network Automation ---- without installing any software at target Nodes. by simple SSH , Also k/A Agentless software as no s/w installed on target Servers.
B22: Ansible Architecture and component
B23: 1. Control Node (Master) -- where Ansible is installed, Execute playbook, it connect target Node via SSH 2. Target Node./ Manager Node --> Remote Server. These are the servers you want to automate 3. Inventory ( Host) --> Its a file where we save IPs or hostnames of target servers . By Default Path /etc/ansible/hosts .We can make Group servers using [web], [db], [lavjeet1] etc. Creathost // nano [web] 192.168.1.10 192.168.1.11 [db] 192.168.1.20
B24: 4. Playbook --> its a yml file where we save instruction to automate the tasks, its like a script --- - name: Install Nginx Playbook hosts: webserver # This refers to the host group defined in your inventory file become: yes # Run tasks with sudo/root privileges tasks: - name: Update Apt package cache apt: update_cache: yes # Equivalent to running 'apt update' - name: Install Nginx apt: name: nginx state: present # Ensures nginx is installed - name: Ensure Nginx is running and enabled service: name: nginx state: started # Make sure nginx service is running enabled: yes # Enable nginx to start on boot # Optional: Open firewall port 80 (only if UFW is being used) - name: Allow HTTP through UFW ufw: rule: allow port: '80' proto: tcp
B25: 6. Roles (Reusable code structure) --> Organize your playbooks into structured folders, Roles like root modules. Roles helps to load automatically variable, files, task, other ansible artifects so that you can reuse them Once you group your content into roles then you can reuse them share them Roles = modular structure to organize your playbook code into folders: tasks/ handlers/ vars/ templates/ files/ defaults/
B26: 7. Modules --> modules allow users to automate wide range of tasks from installing package to manageing services. Module are the small programs that do the actual work. Push bases
B27: 8. Handlers --> handlers are the tasks which only run when notified.
B29: ansible-inventory -i hosts --list
B30: ansible-playbook -i hosts install_nginx.yml
B31: ansible -i hosts weblav -m ping
... B41: DataDog

Sheet Monitoring
B1: MONITORING
B3: 1. PROMETHEUS
B4: 2. GRAFANA
B5: 3. GRAFANA LOKI
B6: 4. AZURE MONITOR
B8: Monitoring Tools
B9:  OPEN SOURCE  1. Prometheus 2. Grafana 3. Grafana Loki
B10:  Paid | C10:  Azure Monitor
B12: 1. Prometheus  Metrics  Numeric Values  Pull based
B13: 2. Grafana LOKI  Logs  Text based values  Push Based
B14: 3. Azure Monitor  Metrics + Logs  Text + Numeric Vaues Push based
B16: Agents
B17: - Agents are small software installed in the machines which we want to monitor
B18: - It is important that they’re running in target machine for continuous monitoring
B19: Node Exporter  Prometheus
B20: Azure Monitor Agent (AMA)  Azure Monitor
B21: Grafana Agent  Grafana
B22: Promtail  Grafana Loki
B24: Push and Pull Model of Monitoring:
B26: 1. Push Model
... B59: ./prometheus --config.file=prometheus.yml
C60: ###This have 3 configuration : global, rule_files, and scrape_configs.
B61: 7. Default port – 9090 for prometheus
B63: 8. Visit http://localhost:9090 when installed locally in your local system
B64:  or change local host to your VMS ip address
B65:  Also If using NSG, enable port 9090 in Networking rules, else it might error out
B67: 9. http://localhost:9090/graph  shows the graph
B68: https://localhost:9090/metrics --> Shows all the metrics
B70: 10. Configuring Prometheus to monitor Node Exporter
B71:  add a job inside scraps_configs key under prometheus.yml file
B72:  change the target with VM ip address + port no
B73:  static_configs:
B74: - targets: [<vms-ipaddr>:<port-no>']
B77: Node Exporter Steps:
... B145: 10. ./prometheus --config.file="prometheus.yml"
C149: DataDog
C150: Datadog is a cloud-based monitoring and observability platform that helps you collect, visualize, and analyze metrics, logs, and traces from your infrastructure, applications, and services in one place.
C151: Datadog is a SaaS-based monitoring, alerting, and observability platform that helps track metrics, logs, and traces across infrastructure, applications, and cloud services.
C152: It gives a centralized view of system health, performance, and security.
C154: How to Integrate Datadog

Sheet GitHub
A1: cheerypick , git pull, git fetch , git merger, git rebase , git fork
D2: Git Command | E2: Purpose | F2: Example
A3: What is Git? | D3: git init | E3: Initialize a new Git repository | F3: git init
A4: Git is distributed version control system where we have a local database as well as a remote database to track file changes. | D4: git clone <url> | E4: Clone a repository | F4: git clone https://github.com/user/repo.git
A5: A distributed version control system to track changes in source code and collaborate on projects. | D5: git status | E5: Show the working directory status | F5: git status
D6: git add <file> | E6: Stage file(s) for commit | F6: git add index.html
A7: What is version control system ( VCS) ? | D7: git add . | E7: Stage all changed files | F7: git add .
A8: A Version Control System (VCS) is a tool that helps developers by saving/managing changes to source code over time. | D8: git commit -m "message" | E8: Commit changes with a message | F8: git commit -m "Initial commit"
A9: Types of Version control System | D9: git push | E9: Push local changes to remote repository | F9: git push origin main
A10: 1. local version control system(LVCS) --> in this code and database both are on local system | D10: git pull | E10: Fetch and merge changes from remote | F10: git pull origin main
A11: 2. Centralized Version Control System (CVCS) --> In this database is stored in a central server. Developers pull from and push code to this central repo. But there is problem i.e. Single point of failure. Means if central server is dead you can't recover your database | D11: git log | E11: View commit history | F11: git log
A12: 3. Distributed Version Control System (DVCS) --> in this, database is at your local system as well as at central server. Changes can be committed locally and pushed later. | D12: git branch | E12: List all branches | F12: git branch
D13: git checkout <branch> | E13: Switch to a different branch | F13: git checkout develop
A14: How do you initialize a Git repository? | D14: git merge <branch> | E14: Merge a branch into the current branch | F14: git merge feature-1
A15: git init — sets up a new Git repo in your project directory. | D15: git remote -v | E15: Show remote repository URLs | F15: git remote -v
D16: git diff | E16: Show differences between files | F16: git diff
A17: What is a commit in Git? | D17: git config | E17: Set Git configuration values | F17: git config --global user.name "John"
A18: A snapshot of your changes, recorded in the repo history using git commit. Git commit -m "put some comment " it wil generate a commit id (A unique commit ID (SHA hash)) | D18: git rebase | E18: Reapply commits on top of another base tip | F18: git rebase main
D19: git cherry-pick | E19: Apply a single commit from one branch to another | F19: git cherry-pick abc1234
A20: How do you create a new branch in Git? | D20: git stash | E20: Temporarily save uncommitted changes | F20: git stash / git stash pop
A21: git branch <branch-name> — creates a new branch from the current commit. git checkout -b <newbranch> -- > also do checkout from 1 branch and parallely create a new branch by using | D21: git hook | E21: Trigger custom scripts before/after Git events (pre-commit, post-merge etc.) | F21: e.g., .git/hooks/pre-commit
D22: git reflog | E22: Show history of branch movements (even deleted commits) | F22: git reflog
A23: How do you switch between branches in Git? | D23: git bisect | E23: Binary search to find the commit that introduced a bug | F23: git bisect start / git bisect good / bad
A24: git checkout <branch-name> or git switch <branch-name>. | D24: git blame | E24: Show who last modified each line of a file | F24: git blame app.py
D25: git shortlog | E25: Summary of commits per author | F25: git shortlog -s -n
A26: What is the purpose of the .gitignore file? | D26: git log --stat | E26: Show changes made in each commit with stats | F26: git log --stat
A27: To exclude files/folders (like logs, temp, .exe files) from being tracked by Git. | D27: git analyze (custom) | E27: Analyze repository size, contributors (not native command) | F27: Use git log, cloc, or third-party tools
A29: What is the difference between git pull and git fetch?
A30: git fetch: it download changes from remote but doesn’t merge them into your local branch. It is Safe way to preview changes before applying them. After fetch, you can view differences using: -> git diff origin/main
A31: git pull: Downloads and merges changes into your current branch. Fetches + auto merges into current branch. | D31: git fetch vs git pull
D32: fetch: Downloads changes from remote, does not merge into your current branch
A33: How do you view the commit history in Git? | D33: pull: Fetches + Git automatically merges remote changes into current branch . git fetch + git merge
A34: git log — shows commit history with hash, author, date, and message.
A35: git log --state --> and git log --oneline | D35: git pull vs git pull --rebase
A36: What is a merge conflict in Git, and how do you resolve it? / How to solve git conflict? | D36: pull: Merge commits (e.g., Merge branch 'main')
A37: When changes clash during merge; resolve manually, then git add + git commit. | D37: pull --rebase: Fetches + rebases your local commits on top of remote Linear history (re-applies your commits on top of fetched ones)
A38: Git conflicts happen when:
A39: Two branches modify the same line(s) in a file. A file is modified in one branch and deleted/re-modify in another branch. | D39: merge vs rebase
A40: When you try to merge branch that time Git will report a conflict and list conflicted files and git will add marker on that line git merge feature/branch . . . <<<<<<< HEAD Your changes on current branch ======= Changes from feature-branch >>>>>>> feature-branch | D40: merge: Keeps all history + shows merge points.
A41: To Solve Git Conflict | D41: rebase: Clean history, better for review but changes commit IDs (rewrites history). Moves/rewrites commits from one branch onto another
A42: 1. run "git status" to get the file name where is conflict 2. Open that file in VS code 3. You can manaually edit that file or In Vs code: conflict will show 3 options -> 1. Accept the current changes ( means it will keep existing file data) 2. Accept the incoming changes ( it will update the new file data ) 3. accept both changes ( it will add keep existing line + also add new file ine) 4. then run git add 5. then git commit -m " put some comment" 6. git merge
D43: git rebase vs git cherry-pick:
A44: What is the difference between git reset and git revert? | D44: git rebase main : Moves all commits from the current branch on top of main. Moves entire branch/series of commits to a new base
A45: reset: Moves HEAD and deletes history (Dangerous & destructive). Or Moves the branch pointer backward to a previous commit. Deletes commits from history (locally). It Can modify staging area and working directory depending on the mode (--soft, --mixed, --hard). git reset --hard <commit-id> | D45: git cherry-pick <commit-hash> : Copies one or more specific commits from one branch to another
A46: revert: Creates a new commit that undoes changes (safe for shared repos). Keeps full commit history intact. git revert <commit-id>
A48: How do you undo the last commit in Git?
A49: git reset --soft <commit-id> (keep changes). / Removes the last commit & Keeps your changes staged
A50: git reset --mixed <commit-id> (discard changes). / Removes the last commit & Keeps changes in your working directory but unstaged.
A51: git reset --hard <commit-id> (discard changes). /Deletes the commit and all changes permanently.
A52: Why not use git revert to undo the last commit? --> git revert doesn't delete the last commit — it adds a new commit. New commit will reflect in the history.
A54: What is Git stash & What is the purpose of the git stash command?
A55: Temporarily saves uncommitted changes so that you can work on something else.
A56: **Git stash** is a command used to temporarily save "your uncommitted changes (both staged and unstaged)" ( you’ve made in your working directory without committing them ). It allows you to switch to another branch or task without losing your current work. Later, you can reapply those changes with `git stash apply` when you're ready.
A57: git stash -> save chages git stash list --> See stash list git stash apply --> Apply the latest stash: git stash pop --> Apply and remove from stash: git stash clear --> Delete all stashes:
A58: Example :- how to use it here you are working any code then run git stash git checkout main # switch to main branch ( other branch) # fix something # now work done here , want to go back on your last working branch git checkout feature/task1 ( checkin to your working branch where you save uncommited changes) git stash pop #it will apply changes and remove from stash
A60: What is Git hooks
... A93: What is the difference between git merge and git rebase?
A94: merge: Keeps commit history with a merge commit. | D94: Azure YAML Pipeline | E94: GitHub Actions
A95: rebase: Rewrites history for cleaner linear commits. | D95: trigger: | E95: on:
D96: pr: | E96: on: pull_request
A97: What is a Git submodule, and how do you use it? | D97: pool: | E97: runs-on:
A98: A sub-repo inside your main repo. Add with git submodule add <repo-url>. | D98: variables: | E98: env:
D99: parameters: | E99: inputs: (in workflow_call or workflow_dispatch)
A100: How do you handle large files in Git? | D100: jobs: | E100: jobs:
A101: Use Git LFS (Large File Storage) to manage large binaries efficiently. | D101: steps: | E101: steps:
D102: task: (built-in tasks) | E102: uses: (for actions)
A103: What is the purpose of git cherry-pick? | D103: script: | E103: run:
A104: To apply a specific commit from one branch to another. | D104: stages: | E104: (Not directly supported — use separate jobs or workflows)
D105: dependsOn: | E105: needs:
A106: How do you rename a branch in Git? | D106: condition: | E106: if:
A107: Current branch: git branch -m <new-name> | D107: template: | E107: uses: (reusable workflow)
D108: name: | E108: name:
A109: Remote: git push origin :old-name <new-name> + git push --set-upstream origin <new-name> | D109: displayName: | E109: name:
D110: checkout: self | E110: uses: actions/checkout@v3
A111: What is the difference between git pull --rebase and git pull? | D111: publish: (artifacts) | E111: uses: actions/upload-artifact@v3
A112: git pull: Fetches + merges (adds merge commit). | D112: download: (artifacts) | E112: uses: actions/download-artifact@v3
A113: git pull --rebase: Re-applies your changes over latest remote (linear history). | D113: continueOnError: | E113: continue-on-error:
D114: timeoutInMinutes: | E114: timeout-minutes:
A117: GIT COMMANDS
A120: pushing the branch for 1st time from any branch
A121: git push -u origin <branch-name>
A123: Stages
A124: Working Directory → Staging Area (Start Track files)
A125: git add <filename>
A127: Staging Area → Local Repo (Push Files to Local repo)
A128: git commit -m “short message”
A130: Local Repository → Cloud
A131: git push
A133: Rename a most recent commit Message
A134: git commit --amend -m "New commit message"
... A180: Advanced

Sheet Company wise
A1: company | B1: Question | C1: topics | D1: aa | E1: Chapter
A2: Admiral India | B2: What are different VMs provided by Azure?
A3: Admiral India | B3: How to create a VM via terraform with external disk attached? | C3: Create VM | E3: Terraform
A4: Admiral India | B4: How to configure a highly available VM?
A5: Admiral India | B5: What is terraform taint? | C5: taint | E5: terraform
A6: Admiral India | B6: Why and how do we use the private end point in Azure? | C6: Endpoint
A7: Admiral India | B7: What is blobe storage? | C7: Storage
A8: Admiral India | B8: Azure active directory? | C8: AAD
A9: Admiral India | B9: Difference in Azure web app and functions?
A10: Admiral India | B10: What is state locking? | C10: Statefile | D10: State locking | E10: Terraform
A11: Admiral India | B11: Can you explain the end to end flow of CICD implementation? | C11: cicd | E11: Pipeline
A12: Admiral India | B12: Have you used the AKS service in Azure? | E12: AKS
A13: Admiral India | B13: What is Entrypoint in dockerfile? | C13: ENTRYPOINT | E13: Docker
A14: Accion | B14: What Docker Architecture. | E14: Docker
A15: Accion | B15: What is ENTRYPOINT and CMD in the docker | C15: ENTRYPOINT | E15: Docker
A16: Accion | B16: What is telemetry.
A17: Accion | B17: What is agent less job in the pipeline.and tell me example. | E17: Pipeline
A18: Accion | B18: I have 20 pods are running and I want to update to 60 what will be proces, whats the process behind this. | E18: Kubernetes
A19: Accion | B19: How you will secure a Azure DevOps.
A20: Accion | B20: Do you know Nagios.
A21: Accion | B21: Have you work on the ansible and jenkins
A22: Accion | B22: have you write a dot net and Java
A23: Accion | B23: What is sonar Qube and why we are using in the pipeline. | E23: Pipeline
A24: Accion | B24: What is storage account,How you access the cred from the pipeline. | C24: Storage | E24: Pipeline
A25: Accion | B25: Other then Azure storege how you will manage the credentilas.
A26: Altimetrik | B26: How you migrate data from cloud init to terraform | E26: terraform
A27: Altimetrik | B27: How you manage state file | C27: Statefile | D27: Manage state file | E27: Terraform
A28: Altimetrik | B28: Write Java based CICD pipeline | C28: cicd | E28: Pipeline
A29: Altimetrik | B29: How you test application
A30: Altimetrik | B30: Write Java based application docker file | E30: Docker
A31: Altimetrik | B31: How we can apply RPO and RTO with Terraform | E31: terraform
A32: Altimetrik | B32: How Ingress controller works
A33: Altimetrik | B33: Difference between stateful and deployment | C33: statefull and stateless
A34: Altimetrik | B34: Did you work on logging tools
A35: Altimetrik | B35: Did you work on Splunk
A36: Altimetrik | B36: What is service mesh
A37: Blazeclan | B37: Tell me about day to day activity and on what tech you want to work in future
A38: Blazeclan | B38: Do you worked as Linux Admin or Window admin
A39: Blazeclan | B39: How you handle if you patches one VM and during reboot it's not coming up
A40: Blazeclan | B40: How you store back ups
A41: Blazeclan | B41: How many replica set there in Storage account | C41: Storage
A42: Blazeclan | B42: Which type of HPA you apply when high memory app required
A43: Blazeclan | B43: How you change the private load balancer to public load balancer. | C43: Loadbalancer
A44: Blazeclan | B44: How you create service connection
A45: Blazeclan | B45: How you ensure the cluster life and its maintenance
A46: Blazeclan | B46: Do you know about PDB
A47: Blazeclan | B47: Do you know about transient rule
A48: Blazeclan | B48: Port rules in Linux
A49: Blazeclan | B49: How you login into VMs and change the disks
A50: Blazeclan | B50: How you pull the image from ACR and push it to AKS | E50: AKS
A51: Blazeclan | B51: Etc/dh file to update the user details (related to upgrade the disk like attach SSD to VM)
A52: Blazeclan | B52: How two same address space VNET will communicate | C52: Vnet
A53: Blazeclan | B53: If A vnet is peered with B and B to C then Will A and C communicate ? | C53: Vnet
A54: Blazeclan | B54: What types of projects are you currently working on?
A55: Blazeclan | B55: Which monitoring tools have you used in your projects?
A56: Blazeclan | B56: How many AKS clusters have you worked with, and are they public or private? Are they Linux-based or Windows-based? | C56: AKS cluster | E56: AKS
A57: Blazeclan | B57: If you encounter an issue with a virtual machine (VM), how would you troubleshoot it?
A58: Blazeclan | B58: How do you connect to a single console on a Windows VM?
A59: Blazeclan | B59: If a VM cannot be restored, how would you create another VM with the same configuration?
A60: Blazeclan | B60: Which command is used to check open ports on a Linux VM?
A61: Blazeclan | B61: How would you add a new data disk to a Linux VM?
A62: Blazeclan | B62: Which load balancer do you consider the best, and why? | C62: Loadbalancer
A63: Blazeclan | B63: If you are unable to log in to an AKS cluster and receive a "request timeout" error, how would you troubleshoot it? | C63: AKS cluster | E63: AKS
A64: Blazeclan | B64: How do you upgrade an AKS cluster? | C64: AKS cluster | E64: AKS
A65: Blazeclan | B65: How does an upgrade process work in a pipeline? | E65: Pipeline
A66: Blazeclan | B66: What is a Pod Disruption Budget (PDB) in Kubernetes? | E66: Kubernetes
A67: Blazeclan | B67: What is kube-proxy, and what is its role in Kubernetes? | E67: Kubernetes
A68: Blazeclan | B68: What is a Container Network Interface (CNI), and how does it work?
A69: Blazeclan | B69: Can you explain the Kubernetes architecture in detail? | E69: Kubernetes
A70: Blazeclan | B70: If a pod is in a crash loop backoff state, how would you troubleshoot the issue? | E70: Kubernetes
A71: Blazeclan | B71: What is the error code for a crash loop backoff issue?
A72: Blazeclan | B72: How do you manage multiple storage accounts (e.g., 50+) and handle individual billing for each? | C72: Storage
A73: Blazeclan | B73: What is the difference between the cold tier and cool tier in a storage account? | C73: Storage
A74: Blazeclan | B74: Which version are you using AKS cluster? How do you upgrade AKS cluster? | C74: AKS cluster | E74: AKS
A75: Blazeclan | B75: How many AKS clusters are you handling along with total nodes in each AKS? | C75: AKS cluster | E75: AKS
A76: Blazeclan | B76: How will you TS if you get imagepullbackoff error while creating any POD? | E76: Kubernetes
A77: Blazeclan | B77: What OOM and How are you going to TS?
A78: Blazeclan | B78: If something goes wrong in your environment you need to create new system pool, What steps will you use to doing that?
A79: Blazeclan | B79: Which linux command to you use to check VM open ports?
A80: Blazeclan | B80: Which command is used in linux to attach any VM disk?
A81: Blazeclan | B81: What is TOP and LVM command in linux?
A82: Blazeclan | B82: Statefile management in terraform? | C82: Statefile | D82: Manage state file | E82: terraform
A83: Blazeclan | B83: What is the best approach to write terraform code? | E83: terraform
A84: Blazeclan | B84: What is UDR and How can you define rules in it?
A85: Capgemini | B85: what is resource group | C85: rg
A86: Capgemini | B86: you have a vnet in one region and another vnet in another region how to communicate both vnet. | C86: Vnet
A87: Capgemini | B87: What are nsg | C87: NSG
A88: Capgemini | B88: we have depoly an application on vm application got popularand we experience suddent increase traffic. what is the concept to address sudden traffic
A89: Capgemini | B89: what is azure storage and its types explain. | C89: Storage
A90: Capgemini | B90: Explain a scenario where we used file share
A91: Capgemini | B91: ⁠ ⁠What is role of traffic manager in azure. | C91: traffic manager
A92: Capgemini | B92: ⁠ ⁠What is azure app service | C92: azure app
A93: Capgemini | B93: What are key managment services provided by Azure
A94: Capgemini | B94: ⁠ ⁠What are the key components of Azure devops
A95: Capgemini | B95: i have created a vm in resource group a and want to move resource group b is it possible if yes how can do it | C95: rg
A96: Capgemini | B96: you have a requirements related to authentication where you need to ensure that when ever any user login it should be prompted to re enter the password
A97: Capgemini | B97: ⁠ ⁠What is terraform life cycle | C97: terraform lifecycle | E97: terraform
A98: Capgemini | B98: What is the purpose of creating a terraform module | C98: Module | E98: terraform
A99: Capgemini | B99: consider a scenario you have asked to create 3 different env in a single azure subscription dedicatied state file in enviroment how can manage | C99: Statefile | D99: Manage state file | E99: Terraform
A100: Capgemini | B100: there is application depolyment on vm requirements to run script through terraform | E100: terraform
...

Sheet 5. K8s
A1: How to move/copy a file inside pod?
A2: To move or copy a file inside a pod, use the `kubectl cp` command. For example, `kubectl cp localfile.txt <pod_name>:/path/in/pod/` copies a file from your local machine to the pod. To copy files from the pod to your local machine, reverse the command like `kubectl cp <pod_name>:/path/in/pod/file.txt localfile.txt`.
A4: 2. **Q: How do you manage configuration in Kubernetes?**
A5: - **A:** Use ConfigMaps to manage configuration data and Secrets to manage sensitive information. Both are used to inject configuration into Pods.
A22: 8. **Q: How do you scale applications in Kubernetes?**
A23: - **A:** Use Horizontal Pod Autoscalers (HPA) to automatically scale the number of Pods based on metrics like CPU utilization or custom metrics.
A34: 12. **Q: How do you monitor and log Kubernetes clusters?**
A35: - **A:** Use monitoring tools like Prometheus and Grafana, and logging solutions like Elasticsearch, Fluentd, and Kibana (EFK stack) or Loki for logging and visualization.
A52: 18. **Q: What are Kubernetes Operators?**
A53: - **A:** Operators are application-specific controllers that extend Kubernetes to manage complex stateful applications, automating tasks like deployment, scaling, and backup.
A81: What are the Steps involved in release management of application
A82: Release management involves: 1. **Planning**: Decide what features or fixes will be included in the release and set a timeline. 2. **Development and Testing**: Develop the code and thoroughly test it to ensure it works correctly. 3. **Deployment and Monitoring**: Release the application to users and monitor its performance to catch any issues early. These steps help ensure a smooth and successful application release.
... A352: you can also check and monitor your any worker node from azure ---> go to k8s cluster and select your cluster --> setting --> node pool --> select your node pool -> nodes--> select any node-->overview --> go down and check montioring

Sheet 1. Terrform
B1: Lifecycle block , Null Resource , Provisioner , locals block, output block, dynamic block, taint, import command, workspace | C1: =VLOOKUP(B1,Nichod.tf!C:D,2,0) -> #N/A
C2: =VLOOKUP(B2,Nichod.tf!C:D,2,0) -> #N/A
A3: 1 | B3: 10. **Q: How do you handle Terraform drift?** | C3: =VLOOKUP(B3,Nichod.tf!C:D,2,0) -> #N/A
B4: - **A:** Terraform drift occurs when changes are made outside of Terraform. Use `terraform plan` to detect drift and then apply updates to reconcile the actual state with the desired state. | C4: =VLOOKUP(B4,Nichod.tf!C:D,2,0) -> #N/A
C5: =VLOOKUP(B5,Nichod.tf!C:D,2,0) -> #N/A
A6: 2 | B6: 11. **Q: How can you use Terraform with version control?** | C6: =VLOOKUP(B6,Nichod.tf!C:D,2,0) -> #N/A
B7: - **A:** Store Terraform configuration files in version control systems like Git. Use branches and pull requests to manage changes and collaborate with team members. | C7: =VLOOKUP(B7,Nichod.tf!C:D,2,0) -> #N/A
C8: =VLOOKUP(B8,Nichod.tf!C:D,2,0) -> #N/A
A9: 3 | B9: 13. **Q: How do you perform Terraform resource tagging?** | C9: =VLOOKUP(B9,Nichod.tf!C:D,2,0) -> #N/A
B10: - **A:** Tags can be applied to resources using configuration settings in the resource block, helping with cost management and organization. For example, `tags = { "Environment" = "Production" }`. | C10: =VLOOKUP(B10,Nichod.tf!C:D,2,0) -> #N/A
B11: we normally used locals block to apply tags at all resource. It will be easy and whenever you need to change tags/ add new tags , just simply add that tag inside locals block and it will auto update to all. ( you not need to go and change tags at every resource) | C11: =VLOOKUP(B11,Nichod.tf!C:D,2,0) -> #VALUE!
B12: locals { comman_tag = { App_id = "Storage_account_with_dynamic" environment = "preprod" cost_center = "lavjeet-cost_center" } stg_specfic_tag = { company = "Nokia" Deparment = "CNS Iptel" } } resource "azurerm_resource_group" "rg_block" { for_each = var.stg_details name = each.value.name location = each.value.location tags = merge(local.comman_tag, local.stg_specfic_tag) } | C12: =VLOOKUP(B12,Nichod.tf!C:D,2,0) -> #VALUE!
C13: =VLOOKUP(B13,Nichod.tf!C:D,2,0) -> #N/A
C14: =VLOOKUP(B14,Nichod.tf!C:D,2,0) -> #N/A
A15: 3 | B15: 20. **Q: How do you roll back changes in Terraform?** | C15: =VLOOKUP(B15,Nichod.tf!C:D,2,0) -> #N/A
B16: Terraform doesn't support automatic rollback. To revert changes, 1st way --> you can manually apply a previous version of the configuration( code) 2nd --> or use version control (like Git) to restore earlier .tf files and re-apply. Or 3rd way --> If you are using VCS then you go to that specific commit by using ( git checkout <commit id> and then you will reach to that specfic commit it and then reapply and merge it | C16: =VLOOKUP(B16,Nichod.tf!C:D,2,0) -> #VALUE!
B17: - **A:** Rolling back changes can be achieved by applying a previous version of the configuration. Always review changes carefully before applying. | C17: =VLOOKUP(B17,Nichod.tf!C:D,2,0) -> #N/A
C18: =VLOOKUP(B18,Nichod.tf!C:D,2,0) -> #N/A
A19: 4 | B19: Why we need terraform? | C19: =VLOOKUP(B19,Nichod.tf!C:D,2,0) -> #N/A
B20: We need Terraform to automate the creation and management of cloud resources, making it easier to set up and maintain infrastructure. It uses configuration files to define what you need, so you can apply changes quickly and consistently. This helps avoid manual errors and saves time by managing infrastructure as code. | C20: =VLOOKUP(B20,Nichod.tf!C:D,2,0) -> #VALUE!
C21: =VLOOKUP(B21,Nichod.tf!C:D,2,0) -> #N/A
A22: 5 | B22: Someone deleted resources manually in portal how can you recover that through terraform? | C22: =VLOOKUP(B22,Nichod.tf!C:D,2,0) -> #N/A
B23: To recover manually deleted resources, you can run terraform apply to re-create them according to your configuration files. Terraform will notice the missing resources and recreate them to match your desired state. This relies on having accurate Terraform configurations that describe the resources you want to restore. | C23: =VLOOKUP(B23,Nichod.tf!C:D,2,0) -> #VALUE!
C24: =VLOOKUP(B24,Nichod.tf!C:D,2,0) -> #N/A
A25: 6 | B25: What if you want to use configurations outside terraform? | C25: =VLOOKUP(B25,Nichod.tf!C:D,2,0) -> #N/A
B26: If you want to use configurations outside Terraform, you can export or extract them in formats like JSON or YAML. These configurations can then be used with other tools or services that support these formats. This allows you to integrate Terraform-managed infrastructure with external systems or tools. | C26: =VLOOKUP(B26,Nichod.tf!C:D,2,0) -> #VALUE!
C27: =VLOOKUP(B27,Nichod.tf!C:D,2,0) -> #N/A
C28: =VLOOKUP(B28,Nichod.tf!C:D,2,0) -> #N/A
A29: 8 | B29: What type of automation tools you have used other than terraform. | C29: =VLOOKUP(B29,Nichod.tf!C:D,2,0) -> #N/A
B30: Besides Terraform, I’ve used Ansible for automating configuration management and software provisioning, Puppet for managing and automating infrastructure with a declarative language, and Chef for automating infrastructure setup and application deployment. These tools help streamline and manage complex IT environments efficiently. | C30: =VLOOKUP(B30,Nichod.tf!C:D,2,0) -> #VALUE!
C31: =VLOOKUP(B31,Nichod.tf!C:D,2,0) -> #N/A
A32: 9 | B32: Which types of resources you have created in Azure. | C32: =VLOOKUP(B32,Nichod.tf!C:D,2,0) -> #N/A
B33: In Azure, I've created Virtual Machines for running applications and services, Azure SQL Databases for storing and managing data, and Azure Kubernetes Service (AKS) for orchestrating containerized applications. These resources help build, deploy, and manage applications in the cloud efficiently. | C33: =VLOOKUP(B33,Nichod.tf!C:D,2,0) -> #VALUE!
C34: =VLOOKUP(B34,Nichod.tf!C:D,2,0) -> #N/A
A35: 10 | B35: What steps you take to deploy a resourse using Terraform / WHat is terraform flow ? | C35: =VLOOKUP(B35,Nichod.tf!C:D,2,0) -> #N/A
B36: To deploy a resource using Terraform, follow these steps: 1.)Write Configuration/ code : Define the desired resource in a .tf file using Terraform's configuration language. 2.)Initialize ( Init) the setup: Run terraform init to set up your working directory and download necessary plugins. 3. Plan : planning changes to see what will be altered 3.)Apply: Use terraform apply to create or update the resource based on your configuration files. This process sets up and manages your infrastructure as defined in your Terraform files. | C36: =VLOOKUP(B36,Nichod.tf!C:D,2,0) -> #VALUE!
C37: =VLOOKUP(B37,Nichod.tf!C:D,2,0) -> #N/A
A38: 13 | B38: You have a requirement to create a scalable web app infrastructure using the terraform , that app consist of a LB and DB , what would be your design and what type of structures of your terraform configuration is going to be. how are you going to deploy these infrastructure. | C38: =VLOOKUP(B38,Nichod.tf!C:D,2,0) -> #VALUE!
B39: To create a scalable web app infrastructure using Terraform, I would design it with the following components: 1.)Load Balancer (LB): Distributes incoming traffic across multiple web servers. 2.)Web Servers: Scale these servers horizontally using a Scaling Group or Virtual Machine Scale Set. 3.)Database (DB): Use a managed service like Azure SQL Database for scalability and reliability. For the Terraform configuration, I would use modules to define and manage the LB, web servers, and DB separately. Deploy by running terraform init to set up, terraform plan to preview changes, and terraform apply to create and configure the infrastructure. | C39: =VLOOKUP(B39,Nichod.tf!C:D,2,0) -> #VALUE!
C40: =VLOOKUP(B40,Nichod.tf!C:D,2,0) -> #N/A
A41: 15 | B41: How to mark same resource to be create before delete after make changes in the code? | C41: =VLOOKUP(B41,Nichod.tf!C:D,2,0) -> #N/A
B42: we have to use lifecycle block here and we have to pass attribute "create_before_destroy = True" then first it will create and then destory. This is used for zero downtime & ensuring a smooth transition. | C42: =VLOOKUP(B42,Nichod.tf!C:D,2,0) -> #N/A
B43: resource "azurerm_public_ip" "example" { name = "example-ip" location = "East US" resource_group_name = "example-rg" allocation_method = "Static" lifecycle { create_before_destroy = true } } | C43: =VLOOKUP(B43,Nichod.tf!C:D,2,0) -> #N/A
C44: =VLOOKUP(B44,Nichod.tf!C:D,2,0) -> #N/A
A45: 16 | B45: 58. Let's suppose how we can allow in terraform that our team member cal't use the incorrect configuration so that our existing resource not destroy | C45: =VLOOKUP(B45,Nichod.tf!C:D,2,0) -> #N/A
B46: 1. Make it a standard practice to review the output of terraform plan before running terraform apply 2. Use prevent_destroy Lifecycle Block: resource "azurerm_resource_group" "example" { name = "example-rg" location = "EastUS" lifecycle { prevent_destroy = true } } When prevent_destroy = true is set, Terraform will prevent the deletion of this resource, even if the configuration is modified to remove it. If someone tries to destroy or remove the resource, Terraform will give an error. | C46: =VLOOKUP(B46,Nichod.tf!C:D,2,0) -> #VALUE!
C47: =VLOOKUP(B47,Nichod.tf!C:D,2,0) -> #N/A
A48: 17 | B48: 42. How do you ignore changes to a resource attribute in Terraform? | C48: =VLOOKUP(B48,Nichod.tf!C:D,2,0) -> #N/A
B49: Changes to a resource attribute can be ignored using the ignore_changes argument in lifecycle block | C49: =VLOOKUP(B49,Nichod.tf!C:D,2,0) -> #N/A
B50: lets suppose manger applied / changed tags at VMs and once you run terraform apply it willl show us 1 to change but if mark ignore_changes = [tags] then it will ignore tags chages | C50: =VLOOKUP(B50,Nichod.tf!C:D,2,0) -> #N/A
B51: resource "azurerm_virtual_machine" "example" { name = "example-vm" location = "East US" size = "Standard_DS1_v2" lifecycle { ignore_changes = [tags] } } | C51: =VLOOKUP(B51,Nichod.tf!C:D,2,0) -> #N/A
C52: =VLOOKUP(B52,Nichod.tf!C:D,2,0) -> #N/A
C53: =VLOOKUP(B53,Nichod.tf!C:D,2,0) -> #N/A
C54: =VLOOKUP(B54,Nichod.tf!C:D,2,0) -> #N/A
A55: 20 | B55: 1. What is Terraform? | C55: =VLOOKUP(B55,Nichod.tf!C:D,2,0) -> #N/A
B56: Terraform is an open-source Infrastructure as Code (IaC) tool developed by HashiCorp. | C56: =VLOOKUP(B56,Nichod.tf!C:D,2,0) -> #N/A
B57: It allows you to define and provision cloud infrastructure using a high-level configuration language called HCL (HashiCorp Configuration Language). | C57: =VLOOKUP(B57,Nichod.tf!C:D,2,0) -> #N/A
B58: you can manage resources across various cloud providers like Azure, AWS, GCP, and even on-prem services. | C58: =VLOOKUP(B58,Nichod.tf!C:D,2,0) -> #N/A
C59: =VLOOKUP(B59,Nichod.tf!C:D,2,0) -> #N/A
A60: 21 | B60: 2. What are the main features of Terraform? | C60: =VLOOKUP(B60,Nichod.tf!C:D,2,0) -> #N/A
B61: Terraform has several key features: | C61: =VLOOKUP(B61,Nichod.tf!C:D,2,0) -> #N/A
B62: 1. Infrastructure as Code (IaC): Define infrastructure in readable .tf files using HCL. | C62: =VLOOKUP(B62,Nichod.tf!C:D,2,0) -> #N/A
B63: 2. Multi-Cloud Support: Works with AWS, Azure, GCP, and many other providers. | C63: =VLOOKUP(B63,Nichod.tf!C:D,2,0) -> #N/A
B64: 3. Declarative Language: You describe the desired state, and Terraform makes it happen. | C64: =VLOOKUP(B64,Nichod.tf!C:D,2,0) -> #N/A
B65: 4. Execution Plan: terraform plan shows what changes will be made before applying them. | C65: =VLOOKUP(B65,Nichod.tf!C:D,2,0) -> #N/A
B66: 5. State Management: Maintains a state file to track current infrastructure and ensure idempotency." | C66: =VLOOKUP(B66,Nichod.tf!C:D,2,0) -> #N/A
C67: =VLOOKUP(B67,Nichod.tf!C:D,2,0) -> #N/A
A68: 22 | B68: 3. What is the difference between Terraform and other IaC tools like Ansible, Puppet, and Chef? | C68: =VLOOKUP(B68,Nichod.tf!C:D,2,0) -> #N/A
B69: Terraform is a declarative IaC tool focused on provisioning infrastructure (e.g., VMs, networks) using providers like AWS, Azure. Terraform: "Create and manage infrastructure." | C69: =VLOOKUP(B69,Nichod.tf!C:D,2,0) -> #N/A
B70: Tools like Ansible, Puppet, and Chef are primarily configuration management tools. Ansible/Puppet/Chef: "Configure what's already created." | C70: =VLOOKUP(B70,Nichod.tf!C:D,2,0) -> #N/A
B71: they’re better for installing software, managing packages, and configuring systems after the infrastructure is up | C71: =VLOOKUP(B71,Nichod.tf!C:D,2,0) -> #N/A
C72: =VLOOKUP(B72,Nichod.tf!C:D,2,0) -> #N/A
A73: 23 | B73: 4. What is a provider in Terraform? | C73: =VLOOKUP(B73,Nichod.tf!C:D,2,0) -> #N/A
B74: A provider is a plugin that helps Terraform interact with cloud platforms and other services. ( basically it is a exe file) | C74: =VLOOKUP(B74,Nichod.tf!C:D,2,0) -> #N/A
B75: Providers are responsible for managing the lifecycle of resources, like creating, reading, updating, and deleting infrastructure. | C75: =VLOOKUP(B75,Nichod.tf!C:D,2,0) -> #N/A
C76: =VLOOKUP(B76,Nichod.tf!C:D,2,0) -> #N/A
C77: =VLOOKUP(B77,Nichod.tf!C:D,2,0) -> #N/A
C78: =VLOOKUP(B78,Nichod.tf!C:D,2,0) -> #N/A
A79: 32 | B79: 10. What is the purpose of the terraform init command? | C79: =VLOOKUP(B79,Nichod.tf!C:D,2,0) -> #N/A
B80: terraform init initializes a working directory & downloads the necessary provider plugins, modules and prepares the environment. It is the first command to run when starting a new project or after modifying backend configurations. | C80: =VLOOKUP(B80,Nichod.tf!C:D,2,0) -> #N/A
B81: once you hit terraform init --> it download create 1 folder .terraform inside of that *.exe file will be there & create 1 terraform.lock.hcl file in which provider version is locked | C81: =VLOOKUP(B81,Nichod.tf!C:D,2,0) -> #N/A
C82: =VLOOKUP(B82,Nichod.tf!C:D,2,0) -> #N/A
A83: 33 | B83: 38. How do you handle provider versioning in Terraform? | C83: =VLOOKUP(B83,Nichod.tf!C:D,2,0) -> #N/A
B84: in Required_provider block there is version argument where we define, provider version | C84: =VLOOKUP(B84,Nichod.tf!C:D,2,0) -> #N/A
C85: =VLOOKUP(B85,Nichod.tf!C:D,2,0) -> #N/A
A86: 34 | B86: 52. How do you use a lock file in Terraform? | C86: =VLOOKUP(B86,Nichod.tf!C:D,2,0) -> #N/A
B87: A lock file (.terraform.lock.hcl) is used to lock provider versions, It helps maintain consistency and reliability across different runs and environments. | C87: =VLOOKUP(B87,Nichod.tf!C:D,2,0) -> #N/A
C88: =VLOOKUP(B88,Nichod.tf!C:D,2,0) -> #N/A
C89: =VLOOKUP(B89,Nichod.tf!C:D,2,0) -> #N/A
A90: 36 | B90: 11. What does the terraform plan command do? | C90: =VLOOKUP(B90,Nichod.tf!C:D,2,0) -> #N/A
B91: terraform plan creates an execution plan, showing what actions Terraform will take to achieve the desired state defined in the configuration. | C91: =VLOOKUP(B91,Nichod.tf!C:D,2,0) -> #N/A
B92: its like to perform a dry run in terraform | C92: =VLOOKUP(B92,Nichod.tf!C:D,2,0) -> #N/A
C93: =VLOOKUP(B93,Nichod.tf!C:D,2,0) -> #N/A
A94: 37 | B94: 32. How do you perform a dry run in Terraform? | C94: =VLOOKUP(B94,Nichod.tf!C:D,2,0) -> #N/A
B95: A dry run in Terraform can be performed using the terraform plan command, which shows the execution plan without making any changes. | C95: =VLOOKUP(B95,Nichod.tf!C:D,2,0) -> #N/A
C96: =VLOOKUP(B96,Nichod.tf!C:D,2,0) -> #N/A
A97: 38 | B97: 12. What is the terraform apply command used for? | C97: =VLOOKUP(B97,Nichod.tf!C:D,2,0) -> #N/A
B98: terraform apply command execute the exectuon plan to reach the desired state of the configuration / applies the changes | C98: =VLOOKUP(B98,Nichod.tf!C:D,2,0) -> #N/A
B99: when you hit terraform what action performed --> | C99: =VLOOKUP(B99,Nichod.tf!C:D,2,0) -> #N/A
B100: 1. first it will do state lock ( accquring state lock) | C100: =VLOOKUP(B100,Nichod.tf!C:D,2,0) -> #N/A
...

Sheet 2.0 Azure 
C1: 101. What is different between Application getway and Front Door
A2: Types of instances offerd by azure | D2: Azure Loadbanacer is regional LB service which works on Layer 4 and route the traffic based on IP and Port. It support Autoscaling and health probe. ( it doesn't support ssl Termination and WAF) | E2: Application gateway is regional traffic management LB service used for hosting multiple applications behind a single IP address, it work on layer 7 and support HTTP HTTPs and route the traffic based on host , url, path, fqdn, host headed and it support SSL termination, WAF, Auto Scaling and Health probe. | F2: Azure Traffic Manage is global Traffic management and routing LB service which route the traffic based on DNS Layer/ DNS resolution and mutil routing methid like proirity weighted etc. It support health probe and doesn't support SSL termination, WAF, auto Scaling | G2: Azure front door is Global loadbalancer and content deleiver Network ( CND) solution which routes the traffic based on URL Path, Geographic locaton and customer rules ( Geographic location means to the nearest avilable backed based on DNS whose latency is low, proximity, health proble and routing rules. It support Layer 7 HTTP, & HTTPs and also support ssl termiaton, WAF, Auto scaling and health probe
A3: General Purpose: ( Balanced CPU-to-memory ratio.) These VMs are like all-rounders. They’re good for everyday tasks, like running websites or small databases etc Compute Optimized: (High CPU-to-memory ratio.) These VMs are designed for tasks that need a lot of processing power, like handling heavy computations or running complex applications. Memory Optimized: ( High memory-to-CPU ratio.) These VMs are built to handle lots of data at once, making them great for applications that need a lot of memory, like big databases. Storage Optimized – High disk throughput and IOPS. GPU – For heavy graphics rendering or ML workloads. High Performance Compute (HPC) – For intensive compute workloads. | C3: Feature | D3: Azure Load Balancer | E3: Azure Application Gateway | F3: Azure Traffic Manager | G3: Azure Front Door
A4: What is Public private and hybrid cloud? | D4: Region Load Balancing service ( like in LB in Database) | E4: Designed for regional traffic management at application layer 7, hosting multiple applications behind a single IP address, microservices, and securing traffic to backend services via WAF. | G4: Its is a global load balancer and content delivery network (CDN) solution. It's ideal for applications needing low-latency, global traffic distribution.
A5: Public Cloud is like renting space on a shared server, where multiple users use the same resources over the internet. Private Cloud is like having your own dedicated server that only you and your organization use. Hybrid Cloud combines both, allowing you to use both public and private clouds to get the best of both worlds, like having a shared workspace and a private office. | C5: Primary Purpose | D5: Regional load balancing at Layer 4 (TCP/UDP) | E5: Regional load balancing at Layer 7 (HTTP/HTTPS) | F5: DNS-based global traffic distribution and routing | G5: Global load balancing and CDN( Content Delivery Netwrok) at Layer 7 (HTTP/HTTPS)
A6: why you are using application gateway as entrypoint? | C6: Traffic Routing | D6: Routes based on IP & port | E6: Routes based on URL path, host header based, and perfect for distributing traffic within a region | F6: Routes traffic based on DNS resolution, multiple routing methods (priority, weighted, etc.) | G6: routes traffic to the nearest available backend ( based on proximity,Latency, healthprobe,routing rules -> nearest) using Anycast IP, ensuring low-latency connections from any region.
A7: Using an Application Gateway as an entry point helps manage and routes web traffic efficiently. It acts like a traffic manager, load balancer and providing security features such as SSL termination. This ensures your website or app runs smoothly and securely by handling incoming traffic before it reaches your servers. Application Gateway is used as the entry point because it offers: Layer 7 (HTTP/HTTPS) load balancing – smart routing based on URL paths or host headers. Web Application Firewall (WAF) – protects against common threats (OWASP Top 10). SSL Termination – offloads SSL/TLS from backend servers. Autoscaling & Zone redundancy – improves availability and performance. | C7: Scope | D7: Regional (single region) | E7: Regional (single region) | F7: Global (multi-region) | G7: Global (multiple regions)
C8: Layer of Operation | D8: Transport Layer (Layer 4) | E8: Application Layer (Layer 7) | F8: DNS Layer (Layer 3) | G8: Application Layer (Layer 7)
A9: /16 and /28 which will have more usable ip | C9: Global or Regional | D9: Regional | E9: Regional | F9: Global | G9: Global
A10: A /16 subnet has more usable IP addresses than a /28 subnet. Specifically, a /16 subnet provides around 65,536 addresses, while a /28 subnet offers only 16 addresses. So, /16 is much larger and can accommodate many more devices or servers. | C10: Key Features | D10: Load balancing, health probes, auto-scaling | E10: SSL termination, URL-based routing, WAF, autoscaling | F10: Traffic routing based on geographic location, performance, and health | G10: Global load balancing, CDN, WAF, fast failover ensure optimal performance and high availability for applications with global users.
C11: Use Case | D11: Simple regional load balancing for TCP/UDP traffic | E11: Application load balancing within a region | F11: Distribute traffic to multiple regions based on DNS responses | G11: Global traffic management and content delivery
A12: What is address prifixes. | C12: Performance Optimization | D12: Optimized for regional traffic within a single region | E12: Optimized for regional traffic within a specific region | F12: Optimized for global routing decisions based on performance, geo-location, etc. | G12: Optimized for low-latency, global content delivery
A13: Specific IP range assigned to a Netwok / vnet. It define the range of IP addresses for a virtual network (VNet) or subnet using CIDR format. Address Prefixes are like specific ranges of IP addresses assigned to a network. This define which IP addresses are included within that range, helping to organize and manage network traffic. Think of it as setting boundaries on a map to define which areas are covered by a particular network. | C13: Web Application Firewall (WAF) | D13: No | E13: Yes | F13: No | G13: Yes
C14: SSL Termination | D14: No | E14: Yes | F14: No | G14: Yes
A15: what is access control (IAM) in azure. | C15: Autoscaling | D15: Yes | E15: Yes | F15: No | G15: Yes
A16: Access Control (IAM) in Azure is a way to manage control access who can access what within your Azure environment. It allows you to assign roles to users, groups, applications, giving them specific permissions. This ensures that only authorized individuals can access or modify resources, enhancing security and management. | C16: Health Probes | D16: Yes (for backend health) | E16: Yes (customizable) | F16: Yes (used for DNS routing decisions) | G16: Yes (for backend health)
C17: Routing Granularity | D17: IP address and port | E17: URL path, host headers, cookies | F17: DNS-based routing decisions (e.g., priority, geographic, latency-based) | G17: URL path, geographic location, custom rules
A18: Explain Managed identity and service connection and service principal | C18: Redundancy and Failover | D18: Regional failover | E18: Limited to regional failover | F18: Global failover and recovery based on DNS configuration | G18: Global failover and disaster recovery
A19: Managed Identity = Passwordless authentication to get access for Azure services. ( Only works within Azure (can’t be used from outside). ( credential managed by Azure itself) Service Principal = Azure identity for apps/tools. ( ( Requires external credential management )) Service Connection = Azure DevOps integration using SP( service Principle) or MI( Managed Identity) Managed Identity is a feature that automatically manages the credentials which is needed to authenticate in Azure services. removing the need for hard-coded credentials. ( WIF) Service Principal is an identity used by applications, scripts, or automation tools to access Azure service securely. You can authenticate using: ( Requires external credential management ) Client ID + Secret Client ID + Certificate Federated Identity (OIDC) (Open id connect) ( Workload identity federation - WIF) Service Connection is used in Azure DevOps to link the azure devops platform to Azure cloud services or external cloud service, enabling pipelines to deploy and manage resources securely. | D19: database me loadbalancer use krte hai ( layer 4 Wala)
D20: Internal Enterprise App for Employees | E20: Microservices Application | F20: Multi-region Disaster Recovery Setup | G20: Public E-commerce Website
A21: what are the methods to create VM ?
A22: You can create a VM in Azure using several methods: Azure Portal, which is a web-based interface for manual setup; Azure CLI, a command-line tool for scripting and automation; and ARM Templates, which are JSON files used to define and deploy infrastructure as code. These methods provide flexibility in how you set up and manage your VMs.
A24: How can you control traffic on VM ?
A25: You can control traffic to a VM using Network Security Groups (NSGs) to allow or deny specific traffic based on rules, Application Gateway to manage web traffic and provide security features, and Load Balancers to distribute incoming traffic evenly across multiple VMs, ensuring efficient and secure access.
A27: Is it possible to increase the disk size after deploying VM if yes how can you do it without effecting its running .
A28: Yes, you can increase the disk size of a VM after deployment without affecting its operation. In the Azure Portal, navigate to the VM's disk settings, Add disk you want to resize, and adjust the size. After saving the changes, it expand the disk within the VM's operating system to use the new space. This process does not require shutting down the VM. ( You can’t reduce disk size )
A30: If you want to login VM without sharing username and password , how you will do that ?
A31: For Linux --> you can use SSH keys for Linux VMs for Windows --> Azure AD authentication for Windows VMs. SSH keys provide a secure method by using public and private key pairs, while Azure AD authentication allows logging in with your Azure Active Directory credentials, enhancing security by avoiding password sharing.
A33: Suppose we have created a VM , and i want to send some script files in those VM , how can i do this ?
A34: You can transfer script files to a VM by using Secure Copy (SCP) for Linux VMs, Remote Desktop Protocol (RDP) for Windows VMs to manually copy files, or Azure Blob Storage, where you upload files to storage and download them from the VM. Each method ensures your scripts reach the VM securely and efficiently.
A36: Define Fault domain and Update domain.
A37: What are the resources you have worked on azure ?
... A50: Session Affinity ensures that a user's requests are always directed towards the same server during their session. This is useful for applications that need to maintain state or track user activity consistently. It helps provide a smooth, continuous experience by keeping the user's interactions with the same server throughout their session.

Sheet 2.1 Azure Basic
A1: 🟢 Beginner-Level (1–30) | D1: 🟡 Intermediate-Level (31–70) | G1: 🔴 Advanced-Level (71–100)
A3: 1. What is Microsoft Azure?
A4: Microsoft Azure is a cloud computing platform devloped by Microsoft.
A5: It provides services like computing, networking, and storage, Databases, AI, and DevOps.
A6: It Supports building, deploying, and managing apps.
A8: 2. What are the benefits of using cloud computing? | G8: 72. How do you ensure disaster recovery in Azure?
A9: Cloud computing offers scalability, cost-efficiency, and high availability and global access. | G9: Use Azure Site Recovery, Backup, and Geo-Replication.
A10: You pay only for what you use. | G10: Set up failover processes for critical applications.
A11: Resources are available on demand. | G11: Test DR plans regularly.
A13: 3. What are the different cloud deployment models in Azure? | G13: 73. What is the difference between Availability Zones and Sets?
A14: Azure supports Public, Private, and Hybrid cloud models. | G14: Availability Zones provide physical isolation across regions.
A15: Public is fully managed by Microsoft. | G15: Availability Sets are used to distribute VMs within a data center.
A16: Hybrid integrates on-prem and cloud resources. | G16: Zones provide higher fault tolerance.
A18: 4. Name the main categories of Azure services. | G18: 74. How does Azure manage service-level agreements (SLAs)?
A19: Azure services include Compute, Networking, Storage, Databases, AI, and DevOps. | G19: Azure SLAs guarantee uptime for services.
A20: They are grouped by function. | G20: They vary depending on the service type and configuration.
A21: Help in building full-stack solutions. | G21: Azure monitors availability to meet SLA standards.
C23: duplicate 2.0 | G23: 75. How do you manage state in Azure Functions?
G24: Azure Functions can use Durable Functions for managing state.
G25: They provide persistence across function invocations.
G26: Durable Functions handle long-running workflows.
A28: 6. What is Azure Portal? | G28: 76. What are durable functions in Azure?
A29: Azure Portal is a web-based UI for managing Azure services. | G29: Durable Functions are a way to manage stateful workflows.
A30: Allows , deployment, and configuration, monitoring | G30: They allow chaining, fan-out, and human intervention.
A31: It supports CLI and automation tools too. | G31: Ideal for complex serverless applications.
A33: 7. What is Azure Resource Manager (ARM)? | G33: 77. How do you monitor microservices in AKS?
A34: ARM allows you to deploy, manage, and monitor Azure resources using tools like Azure Portal, CLI, PowerShell, or ARM templates. In short, ARM helps you organize, secure, and automate Azure resource deployments effectively. | G34: Use Azure Monitor, Log Analytics, and Application Insights.
A35: It provides a unified way to manage infrastructure by treating resources (like VMs, databases, networks) as a group. | G35: Enable monitoring at both pod and container levels.
A36: It supports infrastructure as code through ARM templates (JSON files) for repeatable and automated deployments. ARM ensures role-based access control (RBAC), tagging, and resource grouping, improving security and organization. | G36: Set up alerts and dashboards for visibility.
D38: 38. What is Azure DNS and how is it used? | G38: 78. How do you configure Prometheus/Grafana with Azure Monitor?
D39: Azure DNS is a hosting service for DNS domains that provides name resolution using Microsoft Azure infrastructure. | G39: Integrate Prometheus with Azure Monitor to collect metrics.
D40: It allows you to manage your DNS records using Azure tools and APIs without needing external DNS providers. | G40: Use Grafana to visualize the metrics.
D41: It resolves domain names to IP addresses. Supports traffic routing and custom domain management. | G41: Ensure proper permissions and configurations.
A43: 9. What are Azure Regions and Availability Zones? | C43: duplicate 2.0 | G43: 79. What are Azure Managed Applications?
A44: Regions are physical locations with multiple data centers. | G44: Azure Managed Applications simplify app lifecycle management.
A45: Availability Zones offer high availability within regions. | G45: Provide an automated environment for deploying apps.
A46: They isolate resources for fault tolerance. | G46: Managed by Azure or third-party vendors.
G48: 80. What is Azure Lighthouse?
G49: Azure Lighthouse enables multi-tenant management for service providers.
G50: Allows centralized monitoring and control of customer environments.
G51: Enhances management and governance capabilities.
G53: 81. What is Azure Private Link?
G54: Azure Private Link provides private connectivity to services.
G55: It ensures traffic doesn't traverse the public internet.
G56: Used for secure access to Azure resources.
D58: 42. How does Azure AD Connect work?
D59: Azure AD Connect is a tool that synchronizes on-premises Active Directory with Azure Active Directory.
D60: It supports hybrid identity model by syncing users, groups, and credentials, allowing single sign-on (SSO) across cloud and on-prem apps.
D61: Ensures consistent authentication across environments.
D63: 43. What is Conditional Access in Azure AD? | G63: 83. How do you implement Zero Trust in Azure?
D64: Conditional Access in Azure AD is a policy-based approach to enforce access controls based on conditions like user location, device state, or app sensitivity. | G64: Zero Trust requires verification for every access request.
D65: Controls access to resources for better security. | G65: Use Multi-Factor Authentication (MFA) and Conditional Access policies.
D66: Can enforce MFA or restrict access. | G66: Implement least-privilege access.
D68: 44. How do you create a custom role in Azure? | G68: 84. What is Azure Bicep and how is it different from ARM templates?
D69: Custom roles are defined by creating a JSON file with Name, Description, Actions, NotActions, and AssignableScopes. | G69: Azure Bicep is a simplified syntax for ARM templates.
D70: Specify permissions for resources and actions. | G70: It is easier to read and write.
D71: Assign roles using RBAC to control access. | G71: Bicep compiles to ARM templates.
C73: duplicate 2.0 | G73: 85. What is Azure Arc?
G74: Azure Arc extends Azure services to on-premises and other clouds.
G75: It enables hybrid cloud management.
G76: Supports Kubernetes clusters and data services.
D78: 46. What is Azure Identity Protection?
D79: Azure Identity Protection detects and mitigates identity risks.
D80: Uses machine learning to analyze user behaviors.
D81: Supports risk-based Conditional Access policies.
D83: 47. What is Azure RBAC? | G83: 87. What are Azure Landing Zones?
D84: Azure RBAC (Role-Based Access Control) is a system that manages access to Azure resources by assigning roles to users, groups, or services. | G84: Landing Zones provide best-practice environments for cloud adoption.
D85: Roles define permissions to perform actions like read, write, or delete on resources. | G85: They help organizations implement cloud governance.
D86: Helps in managing who can access what. | G86: Predefined architecture templates for efficient setup.
D88: 48. What is Azure Policy and how is it different from RBAC? | G88: 88. What are Azure Well-Architected Framework pillars?
D89: Azure Policy controls what resources can be deployed and how they must be configured. | G89: The framework has five pillars: cost optimization, operational excellence, performance efficiency, reliability, and security.
D90: RBAC governs permissions for users and groups. RBAC controls who can perform what actions on resources. | G90: Helps design high-quality workloads.
G91: Provides guidance on Azure best practices.
D93: 49. What are Azure Blueprints? | G93: 89. How do you implement infrastructure as code with Terraform in Azure?
D94: Azure Blueprints define a set of resources and policies. | G94: Use Terraform to define and provision Azure resources.
A95: 18. What is Azure Active Directory (AAD)? ( Azure Active Directory (Azure AD) is now also known as Microsoft Entra ID.) | D95: Used for automating resource deployment with compliance. | G95: Write configuration files using HCL (HashiCorp Configuration Language).
A96: Azure AD is a Microsoft’s cloud-based identity and access management (IAM) service that helps organizations securely manage user identities and control access to applications and resources. | D96: Enables consistent environment provisioning. | G96: Apply the code with Terraform CLI.
A97: It provides Single Sign-On (SSO), MFA, and app integration.
A98: 1. Single Sign-On (SSO): Users can access multiple apps (Microsoft 365, Azure Portal, custom apps) with one login. | D98: 50. How do you implement compliance in Azure? | G98: 90. What are Terraform backends and state locking in Azure?
A99: 2.Authentication & Authorization: Supports MFA, conditional access, and role-based access control (RBAC). | D99: Use Azure Policy, Blueprints, and monitoring. | G99: Backends store the state of Terraform configurations.
A100: 3. Integration: Works with on-prem Active Directory, SaaS apps, and custom applications. | D100: Ensure compliance with industry standards (e.g., GDPR). | G100: State locking prevents concurrent changes.
A101: 4. Security: Protects user identities with identity protection, device management, and access policies. | D101: Monitor and remediate non-compliant resources. | G101: Azure supports remote backends for shared state.
A103: 19. What is the difference between Azure AD and on-prem AD? | G103: 91. How do you secure secrets in Azure DevOps pipelines?
A104: Azure AD is a cloud-based identity and access management service from Microsoft. It’s designed for modern cloud applications like Microsoft 365, Azure, and SaaS apps. It supports protocols like OAuth2 and SAML and enables secure access from anywhere over the internet. | G104: Use Azure Key Vault to store secrets securely.
A105: On-premises Active Directory is a traditional directory service used mainly for managing users, computers, and permissions within a local network. Works primarily within a corporate LAN/WAN It uses protocols like LDAP and Kerberos, NTLM and is best suited for domain-joined Windows environments. | G105: Integrate Key Vault with DevOps pipelines.
G106: Implement RBAC for fine-grained access control.
A108: 20. What is Azure Subscription? | G108: 92. What is the use of YAML pipelines in Azure DevOps?
A109: It is Used for billing, access control, and resource management. | G109: YAML pipelines define build, release, and deployment tasks.
A110: it helps in applying role-based access control (RBAC) to manage who can access what within the resources in that particular subscription. Each subscription is associated with a billing account, so the usage and cost of resources are tracked at the subscription level. Organizations can use multiple subscriptions to separate the environments | G110: Store configuration in source code repositories.
A111: Multiple subscriptions can be linked to one account. | G111: Supports version control and CI/CD automation.
A113: 21. What are Azure Tags? | D113: 53. What are Azure Disks and their types? | G113: 93. What is GitOps and how does it relate to Azure?
A114: Tags are key-value pairs that you can assign to Azure resources which helps to organize and manage them. | D114: Azure Disks provide block-level storage for VMs. | G114: GitOps is a methodology for managing infrastructure with Git.
A115: Tags are especially useful for categorizing resources based on things like environment, department, project, or cost center. | D115: Types include Standard HDD, Standard SSD, and Premium SSD. | G115: Uses Git repositories for storing declarative infrastructure code.
A116: For example, I can tag a virtual machine with Environment=Production and Department=Finance. This makes it easier to filter resources, generate reports, or apply policies. | D116: Each has different performance and cost characteristics. | G116: Azure Kubernetes Service (AKS) integrates well with GitOps.
A118: 22. What is Azure Marketplace? | D118: 54. What is Azure File Sync? | G118: 94. What are Azure Monitor Logs and how do you query them using KQL?
A119: Azure Marketplace is a catalog of certified apps and services. | D119: Azure File Sync replicates on-prem files to Azure. | G119: Azure Monitor Logs collect telemetry data from resources.
A120: It includes offerings like virtual machine images, SaaS applications, APIs, and consulting services from both Microsoft and third-party vendors. | D120: Enables hybrid file-sharing between cloud and on-prem. | G120: Use KQL (Kusto Query Language) to query and analyze logs.
A121: Azure Marketplace helps speed up solution deployment and simplifies integration of third-party tools into Azure environments. | D121: Improves disaster recovery and scalability. | G121: Helps monitor and troubleshoot applications.
A123: 23. What is Azure CLI and how is it used? | D123: 55. What are Azure Queues and how are they used? | G123: 95. How do you implement CI/CD with Azure Kubernetes Service?
A124: Azure CLI is a command-line tool to manage Azure. | D124: Azure Queues store and manage messages. | G124: Use Azure DevOps to automate build and deployment pipelines.
...

Sheet 3. CI CD Pipeline
A1: 1 | B1: What is an Azure Pipeline?
B2: Azure Pipelines is a cloud based CI/CD( Continous Integration and Continous Delivery ) service in Azure DevOps that automates the build, test, and deloying codes. It supports various languages and platforms and integrates with GitHub, Bitbucket, and other repositories for continuous integration and delivery.
A4: 2 | B4: How do you set up Continuous Integration (CI) in Azure DevOps?
B5: Configure a build pipeline with triggers that run automatically on code commits or pull requests, integrating build and test processes into the CI workflow.
A7: 3 | B7: Explain the benefits of ci/cd pipelines.
B8: CI/CD pipelines automate the process of integrating code changes (Continuous Integration) and deploying them (Continuous Deployment) quickly and reliably. This ensures code is tested and deployed consistently, reducing manual errors and speeding up delivery. It helps teams release updates more frequently and with greater confidence.
A10: 4 | B10: How do you define a pipeline in Azure DevOps?
B11: To define pipeline we use YAML File( default name azure-pipelines.yml). In this yaml file we define stages, jobs, steps, and task ( build , test, deloy).
B12: we can also create pipeline using Azure Devops ( ADO ) GUI… Classic editior
A14: 5 | B14: What is a YAML pipeline in Azure DevOps?
B15: A YAML pipeline is a pipeline defined using YAML syntax, offering version control for pipeline configurations and enabling complex workflows.
B16: A YAML pipeline is a text-based way to define your CI/CD process in Azure DevOps using a .yml file. It describes how your code should be built, tested, and deployed.
B17: Types of YAML Pipelines in Azure DevOps -> (pipeline definitions --> pipeline: Ste, pipeline: jobs, pipeline: stages, pipeline:extend --> Pipeline that extends a template.)
B18: 1. Single-Stage Pipeline - > A basic pipeline that includes just one job/stage.
B19: 2. Multi-Stage Pipeline --> Combines Build, Test, and Deploy stages in one YAML file.
B20: 3. Templated YAML Pipeline --> Breaks large pipelines into reusable templates.
B21: 4. Environment-based Pipeline --> Uses environment: to deploy to specific targets.
B22: 5. Matrix Strategy Pipeline --> Used for parallel builds across different environments, versions, or configs.
A24: 9 | B24: Explain your pipeline strategy.
B25: My pipeline strategy involves: 1.)Automated Builds: Code changes trigger automatic builds and tests to ensure new code integrates well and is error-free. 2.)Staging Deployments: Successful builds are deployed to a staging environment for further testing before production. 3.)Continuous Deployment: Once verified, the code is automatically deployed to production, ensuring fast and reliable updates with minimal manual intervention. This strategy ensures code quality and smooth deployment with minimal manual effort.
A27: 10 | B27: How do you handle secrets in Azure Pipelines?
B28: Use Azure DevOps Pipelines’ built-in secret management by defining secrets in the pipeline variables or using Azure Key Vault.
A30: 19 | B30: How can you create and use deployment slots in Azure DevOps?
B31: Deployment slots are used in Azure App Services to stage and test deployments before swapping to production. Define slots in your deployment pipeline for staging.
A33: 20 | B33: How do you set up parallel jobs in Azure Pipelines?
B34: In Azure Pipelines, you can run multiple jobs in parallel to speed up your build or deployment process. This is especially useful for testing on multiple environments, parallel deployments, or splitting workloads. Define parallel jobs in your pipeline YAML file or configure them in the visual designer to run multiple tasks simultaneously, improving build times.
B35: 1. Parallel Jobs Using Multiple jobs in a stage
B36: 2. Parallel strategy.matrix for Multiple Configs
B37: stages: - stage: Build jobs: - job: Job1 displayName: "Run Unit Tests" pool: vmImage: 'ubuntu-latest' # Agent for Job1 steps: - script: echo "Running unit tests..." - job: Job2 displayName: "Run Linting" pool: vmImage: 'windows-latest' # Agent for Job2 steps: - script: echo "Running lint checks..." - job: Job3 displayName: "Build Code" pool: vmImage: 'ubuntu-latest' # Agent for Job3 steps: - script: echo "Building application..."
A38: 21 | B38: How do you enable multi-stage deployments in Azure DevOps?
B39: Multi-stage deployments allow you to define build, test, and deploy workflows in a single YAML pipeline, split into stages. each stage representing a different phase of the deployment process. This helps in managing multiple environments like Dev → QA → Prod, with clear approvals, gates, and traceability.
A41: 22 | B41: How do you use Azure Pipelines to deploy to Kubernetes?
B42: Use Azure Pipelines to build Docker images, push them to a Azure container registry( ACR), and deploy them to a Kubernetes cluster using Kubernetes manifests or Helm charts.
A44: 23 | B44: How can you monitor pipeline performance and logs?
B45: Use the built-in Azure DevOps monitoring tools to view pipeline runs, logs, and performance metrics to diagnose issues and optimize workflows.
A47: 24 | B47: How do you create a terraform pipeline, explain the stages and all.
B48: To create a Terraform pipeline: 1.)Setup Stage: Initialize Terraform and download necessary plugins with terraform init. 2.)Plan Stage: Run terraform plan to review proposed changes and ensure they are correct before applying. 3.)Apply Stage: Use terraform apply to create or update resources as defined in the Terraform configuration. These stages automate the process of managing and deploying infrastructure, ensuring consistent and reliable changes.
A50: 25 | B50: What are variable groups in CI/CD pipelines ?
B51: Variable Groups in CI/CD pipelines are collections of variables that you define and manage centrally. They store values like connection strings or API keys, which can be shared across multiple pipelines. This helps keep your configurations organized and makes it easy to update values in one place.
A53: 26 | B53: Pipeline A should be run afte Pipeline B. How we will achive this.
B54: To run Pipeline A after Pipeline B, you can set up a pipeline trigger where Pipeline A is configured to start only when Pipeline B completes successfully. This can be done using pipeline dependencies or completion triggers in your CI/CD tool. This ensures that Pipeline A waits for Pipeline B to finish before it begins.
A56: 29 | B56: How do you configure automatic triggers in Azure Pipelines?
B57: Set up triggers in your pipeline configuration to automatically start builds or releases based on code changes, branch updates, or schedule.
A60: 31 | B60: Aspect : Description
B61: Identity in Azure AD : An app registration is an identity object in Azure AD, representing an application's identity for interaction with Azure AD and Azure resources.
B62: Creation and Configuration : Involves creating an entry for the application in Azure AD and configuring settings such as authentication methods, permissions, and other properties.
B63: Authentication Methods : During app registration, specify how the application authenticates to Azure AD, including client secrets, certificates, or managed identities.
B64: Permissions and Roles : Define the permissions needed by the application to access specific Azure resources. Permissions are assigned through roles like Contributor or Reader.
B65: Redirect URIs : For applications involving user sign-ins, define redirect URIs used to redirect users back to the application after authentication.
B66: Application and Directory IDs : Each app registration has a unique Application (Client) ID and belongs to a specific Azure AD directory identified by a unique Directory (Tenant) ID. These IDs are used for authentication and authorization.
B67: API Permissions : Specify API permissions if the application needs to access other APIs (e.g., Microsoft Graph API). Ensures authorization to make requests to these APIs.
B68: Certificates and Secrets : Configure certificates or client secrets based on the chosen authentication method. Used for authenticating the application when accessing Azure resources.
B69: Service Principals : An app registration automatically creates a service principal in Azure AD. The service principal is an instance representing the runtime identity of the application.
B70: Managed Identities : App registrations can be associated with managed identities for simplified authentication. Managed identities are automatically created identities associated with Azure resources.
B71: Delegated Permissions : Define delegated permissions for applications acting on behalf of users, allowing them to access resources on behalf of users.

Sheet 4. Docker
A7: What is a Docker container?**
A8: lightweight, portable, and self-sufficient unit that packages an application and its dependencies
A10: How do you create a Docker image?**
A11: by writing a `Dockerfile` with the necessary instructions and building it using the `docker build` command.
A13: What is the difference between `docker run` and `docker-compose up`?**
A14: docker run` starts a single container, docker-compose up` launches multiple containers defined in a `docker-compose.yml` file
A16: How can you manage Docker container networking?**
A17: Use Docker’s network modes, such as bridge, host, or overlay networks, and define custom networks in Docker Compose to manage container communication.
A19: What are Docker volumes and how are they used?**
A20: Docker volumes are used to persist data generated by and used by Docker containers. They allow data to be shared between containers and survive container restarts.
A22: How do you optimize Docker images?**
A23: Optimize Docker images by using a minimal base image, combining commands in a single `RUN` statement, and removing unnecessary files and layers.
... A165: docker run -p 8000:8000 my-python-app

Sheet Sheet1
B1: pipeline | C1: mutilstage pipeline ( monolithic & microservices)
C2: mutil environment single pipeline
C3: rollback pipeline
C4: variables
C5: trigger --> Pull based, branchbases, pathbased , pipeline to pipeline trigger | G5: terraform
C6: parameter | G6: azure
C7: selfhosted , microsoft hosted agents | G7: Monitoring Tools
C8: Serivice principle | G8: Git
C9: service connection | G9: CicD pipeline
C10: WIF and working ( OIDC) | G10: docker
G11: k8s
B12: azure | C12: webapp, rollbackup in webapp,
C13: difference b/w webapp and VM
C14: deployment slot vs deployment center | G14: scanning tools
C15: fucntion app
C16: azure services names ( at least 15 service)
C17: azure service provisioned by terraform
C18: Application gw
C19: loadbalancer
B21: k8s | C21: services or network service
C22: ingress.. How it worrks
C23: ingress khan place hot hai cluster ke andar aur cluster ke bahar
C24: scheduler
C25: controller - deployment, replicaset, statefullset
C26: CNI plugin
C27: volume - pvc, pv , configmap, secret
C28: yml - deployment .yml
C29: helm
C30: github action
C31: gitops / argocd

Sheet Sheet3
A1: Hello, I’m Lavjeet Kumar. I bring over 10 years of experience in IT, with 4+ years specifically in DevOps. Currently, I’m working as a Senior DevOps Engineer at Infinite Computer Solutions, where I specialize in Azure Cloud, Terraform, Azure DevOps CI/CD pipelines, Docker, and Kubernetes. I also have hands-on experience with monitoring tools like Grafana and Prometheus. At present, I’m working on the MRF (Media Resource Function) project for a Mexico-based telecom client. I manage the end-to-end DevOps lifecycle, including infrastructure provisioning, automation, and CI/CD pipeline management. For infrastructure provisioning, I use Terraform to automate the deployment of Azure resources such as resource groups, virtual networks, subnets, network security groups, and virtual machines for frontend, backend, and database layers. On the CI/CD side, I design and maintain pipelines in Azure DevOps, enabling seamless integration and delivery across multiple environments. We use GitHub for version control and team collaboration. About the MRF project: The Media Resource Function is a core component of telecom architecture, responsible for audio mixing, voice transcoding, conferencing, announcements, and tone detection in VoIP and IMS environments. Because of its critical nature, we’ve implemented a Hub-and-Spoke architecture to ensure high availability and secure isolation between application environments. The application itself follows a 3-tier architecture: Frontend: Built with ReactJS Backend: Combination of Java and .NET Database: Hosted both in Azure cloud and on-premises Looking forward, we’re working on migrating the application from a monolithic to a microservices-based architecture. For this, we’ve set up sandbox environments for development and testing. We use Azure Kubernetes Service (AKS) to orchestrate containerized workloads for better scalability and manageability. To monitor performance and system health, we’ve integrated Grafana and Prometheus into our workflow. That’s a brief about me. Thank you!
A5: Hello, I’m Lavjeet Kumar I have more than 10 years of experience, out of which 6+ years of experience in DevOps. Currently, I’m serving as a Senior DevOps Engineer at Infinite computer Solutions assoicated with Nokia Solution since 6+ year. I have good knowledge about Azure cloud, Terraform, ADO, CICD Pipeline, Docker, and Kubernetes. And I also have good understanding of monitoring tools such as Grafana and Prometheus. I also have handson experiece on Tools like Tfsec, tflint, tfswitch, triviy, checkovs, sonarqube,. I also have knowledge of ansible. At present, I’m working on MRF project of a Mexico-based client where I handle end-to-end DevOps processes, including infrastructure provisioning automation, and CI/CD pipeline management. I use Terraform IAC tool for Infrastructure provisioning a of Azure cloud resources. This includes provisioning of Resource group, VNET, Subnet NSG Virtual Machines (VMs) for frontend and backend and database infra setup. For automation, I design and implement CI/C¬D pipelines using ADO for continuous integration and delivery of the MRF application across various environments. I also use GitHub for version control. Let me tell you use case of my Project: MRF, Media Resource Function application which is a critical part of cloud infrastructure. It handles media-related operations such as audio mixing , voice transcoding, audio conferencing, playing announcements, and tone detection. it required highly secured and highly available infrastructure, for this we have adopted a Hub and Spoke model. The Hub serves as the central connectivity point, linking multiple isolated Spokes for specific application environments. This application has 3 component, frontend backend and database, frontend is build ReactJs and backend is mix of java and .Net, and database is hosted on both cloud and on premise, this overall 3-tier architecture for which resource provisioning required over azure could. Looking ahead, we’re planning to migrate the MRF application from a monolithic to a micro services architecture. For this, we’ve set up sandbox environments for the initial phases of development and testing. For containerized workloads, I utilize Azure Kubernetes Service (AKS) to orchestrate MRF applications, ensuring scalability and ease of management. We’ve integrated Grafana and Prometheus into our workflow for monitoring and performance tracking. That’s all about me. Thank you!
